mbu_process_dashboard_shared_components/__init__.py
mbu_process_dashboard_shared_components/process.py
mbu_process_dashboard_shared_components/process_dashboard_client.py
mbu_process_dashboard_shared_components/process_run.py
mbu_process_dashboard_shared_components/process_step.py
mbu_process_dashboard_shared_components/process_step_run.py
mbu_process_dashboard_shared_components-1.2.0.dist-info/licenses/LICENSE
mbu_process_dashboard_shared_components-1.2.0.dist-info/METADATA
mbu_process_dashboard_shared_components-1.2.0.dist-info/WHEEL
mbu_process_dashboard_shared_components-1.2.0.dist-info/top_level.txt
mbu_process_dashboard_shared_components-1.2.0.dist-info/RECORD
