Metadata-Version: 2.4
Name: mbu_process_dashboard_shared_components
Version: 1.2.0
Summary: Repo containing functionality related to the process dashboard
Author-email: MBU <rpa@mbu.aarhus.dk>
License-Expression: MIT
Classifier: Programming Language :: Python :: 3
Classifier: Operating System :: Microsoft :: Windows
Requires-Python: >=3.7
License-File: LICENSE
Requires-Dist: mbu-rpa-core
Requires-Dist: cryptography>=43.0.0
Requires-Dist: pyodbc>=5.1.0
Requires-Dist: python-dateutil==2.9.*
Requires-Dist: openpyxl>=3.1.2
Requires-Dist: pandas>=2.2.3
Requires-Dist: office365-rest-python-client
Requires-Dist: pillow
Requires-Dist: ruff
Requires-Dist: sqlalchemy>=2.0.20
Requires-Dist: sqlalchemy[asyncio]>=2.0.20
Requires-Dist: psutil
Dynamic: license-file
